twikit_grok/__init__.py
twikit_grok/client.py
twikit_grok/constants.py
twikit_grok/content.py
twikit_grok/conversation.py
twikit_grok/utils.py
twikit_grok-0.0.2.dist-info/LICENSE
twikit_grok-0.0.2.dist-info/METADATA
twikit_grok-0.0.2.dist-info/WHEEL
twikit_grok-0.0.2.dist-info/top_level.txt
twikit_grok-0.0.2.dist-info/RECORD
