Metadata-Version: 2.1
Name: twikit_grok
Version: 0.0.2
Summary: Twikit Grok
Home-page: https://github.com/d60/twikit_grok
License: MIT
Requires-Python: >=3.8
License-File: LICENSE
Requires-Dist: twikit
